Metadata-Version: 2.1
Name: jjy
Version: 0.0.3.5
Summary: jjy ai framework
Home-page: https://github.com/woduq1414/deep-learning-without-framework
Author: jjy37777
Author-email: jjy37777@naver.com
License: UNKNOWN
Platform: UNKNOWN
Classifier: Programming Language :: Python :: 3
Classifier: License :: OSI Approved :: MIT License
Classifier: Operating System :: OS Independent
Requires-Python: >=3.6
Requires-Dist: numpy (>=1.19.5)
Requires-Dist: tqdm (==4.60.0)
Requires-Dist: jsonpickle (==2.0.0)
